dff_sphinx_theme/__init__.py
dff_sphinx_theme/breadcrumbs.html
dff_sphinx_theme/cookie_banner.html
dff_sphinx_theme/footer.html
dff_sphinx_theme/layout.html
dff_sphinx_theme/layout_footer.html
dff_sphinx_theme/layout_head.html
dff_sphinx_theme/layout_menu.html
dff_sphinx_theme/layout_mobile.html
dff_sphinx_theme/layout_navigation.html
dff_sphinx_theme/scripts.html
dff_sphinx_theme/search.html
dff_sphinx_theme/searchbox.html
dff_sphinx_theme/theme.conf
dff_sphinx_theme/theme_variables.jinja
dff_sphinx_theme/extras/__init__.py
dff_sphinx_theme/extras/custom_directives.py
dff_sphinx_theme/extras/generate_notebook_links.py
dff_sphinx_theme/extras/regenerate_apiref.py
dff_sphinx_theme/static/images/arrow-down-orange.svg
dff_sphinx_theme/static/images/arrow-right-with-tail.svg
dff_sphinx_theme/static/images/arrow_down.svg
dff_sphinx_theme/static/images/chevron-down-black.svg
dff_sphinx_theme/static/images/chevron-down-grey.svg
dff_sphinx_theme/static/images/chevron-down-orange.svg
dff_sphinx_theme/static/images/chevron-right-orange.svg
dff_sphinx_theme/static/images/chevron-right-white.svg
dff_sphinx_theme/static/images/icon-close.svg
dff_sphinx_theme/static/images/icon-menu-dots-dark.svg
dff_sphinx_theme/static/images/logo-facebook-dark.svg
dff_sphinx_theme/static/images/logo-icon.svg
dff_sphinx_theme/static/images/logo-twitter-dark.svg
dff_sphinx_theme/static/images/logo-youtube-dark.svg
dff_sphinx_theme/static/images/logo.svg
dff_sphinx_theme/static/images/pytorch-colab.svg
dff_sphinx_theme/static/images/pytorch-download.svg
dff_sphinx_theme/static/images/pytorch-github.svg
dff_sphinx_theme/static/images/pytorch-x.svg
dff_sphinx_theme/static/images/search.svg
dff_sphinx_theme/static/images/view-page-source-icon.svg
dff_sphinx_theme/static/scripts/theme.min.js
dff_sphinx_theme/static/styles/theme.css
dff_sphinx_theme-0.1.21.dist-info/LICENSE
dff_sphinx_theme-0.1.21.dist-info/METADATA
dff_sphinx_theme-0.1.21.dist-info/WHEEL
dff_sphinx_theme-0.1.21.dist-info/entry_points.txt
dff_sphinx_theme-0.1.21.dist-info/top_level.txt
dff_sphinx_theme-0.1.21.dist-info/RECORD
