Metadata-Version: 2.1
Name: dff-sphinx-theme
Version: 0.1.21
Summary: Dialog Flow Framework Sphinx Theme is a sphinx theme for building DFF distributed website
Home-page: https://github.com/deeppavlov/dff_sphinx_theme
Author: Alexander Sergeev
Author-email: shveitsar215@gmail.com
License: MIT License
Classifier: Development Status :: 4 - Beta
Classifier: Environment :: Web Environment
Classifier: Intended Audience :: Developers
Classifier: Intended Audience :: System Administrators
Classifier: License :: OSI Approved :: MIT License
Classifier: Operating System :: OS Independent
Classifier: Programming Language :: Python
Classifier: Topic :: Internet
Classifier: Topic :: Software Development :: Documentation
Classifier: Programming Language :: Python :: 3
Classifier: Programming Language :: Python :: 3.7
Classifier: Programming Language :: Python :: 3.8
Classifier: Programming Language :: Python :: 3.9
Classifier: Programming Language :: Python :: 3.10
Classifier: Programming Language :: Python :: 3.11
Classifier: Programming Language :: Python :: 3 :: Only
Requires-Python: >=3.6, <4
License-File: LICENSE
Requires-Dist: sphinx (>=5.2.2)
Requires-Dist: sphinx-gallery (==0.7.0)
Requires-Dist: docutils (>=0.19)
